README.md
setup.py
maverick/__init__.py
maverick/evaluate.py
maverick/train.py
maverick/common/constants.py
maverick/common/metrics.py
maverick/common/util.py
maverick/data/datasets.py
maverick/data/pl_data_modules.py
maverick/models/__init__.py
maverick/models/maverick_model.py
maverick/models/model_incr.py
maverick/models/model_mes.py
maverick/models/model_s2e.py
maverick/models/pl_modules.py
maverick/models/test.py
maverick/utils/__init__.py
maverick/utils/logging.py
maverick/utils/loggingl.py
maverick/utils/sampler.py
maverick/utils/upload_to_hf.py
maverick_coref.egg-info/PKG-INFO
maverick_coref.egg-info/SOURCES.txt
maverick_coref.egg-info/dependency_links.txt
maverick_coref.egg-info/not-zip-safe
maverick_coref.egg-info/requires.txt
maverick_coref.egg-info/top_level.txt