Metadata-Version: 2.1
Name: maverick-coref
Version: 0.1.3
Summary: UNKNOWN
Home-page: https://github.com/sapienzanlp/maverick-coref
Author: Giuliano Martinelli
Author-email: giuliano.martinelli97@gmail.com
License: UNKNOWN
Platform: UNKNOWN
Requires-Python: >=3.8.0
